pptestnowakmichal/__init__.py
pptestnowakmichal/m_mod_pptest.py
pptestnowakmichal-0.0.1.dist-info/LICENSE.txt
pptestnowakmichal-0.0.1.dist-info/METADATA
pptestnowakmichal-0.0.1.dist-info/WHEEL
pptestnowakmichal-0.0.1.dist-info/top_level.txt
pptestnowakmichal-0.0.1.dist-info/RECORD
