Metadata-Version: 2.1
Name: pptestnowakmichal
Version: 0.0.1
Summary: My test package
Author-email: mn <noszo997@gmail.com>
License: MIT License
Keywords: pptestnowakmichal,funny functions,name,surname
Classifier: Framework :: IDLE
Requires-Python: >=3.0
License-File: LICENSE.txt
Requires-Dist: numpy ; python_version >= "3.0"
